Workbook

Sheet SUMMARY
A1: Particulars | B1: Inflow | C1: Outflow | D1: Net NPV | E1: Decision
A3: Case 1 | B3: =' CASE 1'!B12 -> -60000000 | C3: =' CASE 1'!I15 -> 81405865 | D3: =B3+C3 -> 21405865 | E3: We will Accept the project due to positive NPV
A5: Case 2 | B5: ='CASE 2'!B12 -> -90000000 | C5: ='CASE 2'!I15 -> 1.11008e+08 | D5: =B5+C5 -> 21007998 | E5: We will Accept the project due to positive NPV
A7: Case 3 | B7: ='CASE 3'!B12 -> -60000000 | C7: ='CASE 3'!I15 -> 90815767 | D7: =B7+C7 -> 30815767 | E7: We will Accept the project due to positive NPV
A9: Case 4 | B9: ='CASE 4'!B12 -> -90000000 | C9: ='CASE 4'!I15 -> 90815767 | D9: =B9+C9 -> 815767.05 | E9: We will Accept the project due to positive NPV

Sheet  CASE 1
A1: Case 1
B2: Yr | C2: Yr | D2: Yr | E2: Yr | F2: Yr | G2: Yr | H2: Yr
A3: Particulars | B3: 0 | C3: 1 | D3: 2 | E3: 3 | F3: 4 | G3: 5 | H3: 6
A4: Sales Unit | C4: 120000 | D4: 120000 | E4: 120000 | F4: 120000 | G4: 120000 | H4: 120000
A5: Price PU | C5: 700 | D5: 700 | E5: 700 | F5: 700 | G5: 700 | H5: 700
A6: Revenue (A) | C6: =C4*C5 -> 84000000 | D6: =D4*D5 -> 84000000 | E6: =E4*E5 -> 84000000 | F6: =F4*F5 -> 84000000 | G6: =G4*G5 -> 84000000 | H6: =H4*H5 -> 84000000
A7: Cost PU | C7: 535 | D7: 535 | E7: 535 | F7: 535 | G7: 535 | H7: 535
A8: Total Cost (B) | C8: =C4*C7 -> 64200000 | D8: =D4*D7 -> 64200000 | E8: =E4*E7 -> 64200000 | F8: =F4*F7 -> 64200000 | G8: =G4*G7 -> 64200000 | H8: =H4*H7 -> 64200000 | K8: Yr
A10: Operating Profit (A-B) | C10: =C6-C8 -> 19800000 | D10: =D6-D8 -> 19800000 | E10: =E6-E8 -> 19800000 | F10: =F6-F8 -> 19800000 | G10: =G6-G8 -> 19800000 | H10: =H6-H8 -> 19800000
A12: Net (Outflow)/Inflow | B12: =-(15000000*4) -> -60000000 | C12: =C10 -> 19800000 | D12: =D10 -> 19800000 | E12: =E10 -> 19800000 | F12: =F10 -> 19800000 | G12: =G10 -> 19800000 | H12: =H10 -> 19800000
A13: PV @ 12 % | B13: 1 | C13: 0.89285714 | D13: 0.79719388 | E13: 0.71178025 | F13: 0.63551808 | G13: 0.56742686 | H13: 0.50663112
A15: PV * Amount | B15: =B12*B13 -> -60000000 | C15: =C12*C13 -> 17678571 | D15: =D12*D13 -> 15784439 | E15: =E12*E13 -> 14093249 | F15: =F12*F13 -> 12583258 | G15: =G12*G13 -> 11235052 | H15: =H12*H13 -> 10031296 | I15: =SUM(C15:H15) -> 81405865
I17: =B15+I15 -> 21405865 | J17: NPV
J18: NPV is positive, so this project is beneficial for us
H27: Case 1 | I27: =I17 -> 21405865
H28: Case 2 | I28: 21007998

Sheet CASE 2
A1: Case 2
B2: Yr | C2: Yr | D2: Yr | E2: Yr | F2: Yr | G2: Yr | H2: Yr
A3: Particulars | B3: 0 | C3: 1 | D3: 2 | E3: 3 | F3: 4 | G3: 5 | H3: 6
A4: Sales Unit | C4: 120000 | D4: 120000 | E4: 120000 | F4: 120000 | G4: 120000 | H4: 120000
A5: Price PU | C5: 700 | D5: 700 | E5: 700 | F5: 700 | G5: 700 | H5: 700
A6: Revenue (A) | C6: =C4*C5 -> 84000000 | D6: =D4*D5 -> 84000000 | E6: =E4*E5 -> 84000000 | F6: =F4*F5 -> 84000000 | G6: =G4*G5 -> 84000000 | H6: =H4*H5 -> 84000000
A7: Cost PU | C7: 475 | D7: 475 | E7: 475 | F7: 475 | G7: 475 | H7: 475
A8: Total Cost (B) | C8: =C4*C7 -> 57000000 | D8: =D4*D7 -> 57000000 | E8: =E4*E7 -> 57000000 | F8: =F4*F7 -> 57000000 | G8: =G4*G7 -> 57000000 | H8: =H4*H7 -> 57000000
A10: Operating Profit (A-B) | C10: =C6-C8 -> 27000000 | D10: =D6-D8 -> 27000000 | E10: =E6-E8 -> 27000000 | F10: =F6-F8 -> 27000000 | G10: =G6-G8 -> 27000000 | H10: =H6-H8 -> 27000000
A12: Net (Outflow)/Inflow | B12: =-90000000 -> -90000000 | C12: =C10 -> 27000000 | D12: =D10 -> 27000000 | E12: =E10 -> 27000000 | F12: =F10 -> 27000000 | G12: =G10 -> 27000000 | H12: =H10 -> 27000000
A13: PV @ 12 % | B13: 1 | C13: 0.89285714 | D13: 0.79719388 | E13: 0.71178025 | F13: 0.63551808 | G13: 0.56742686 | H13: 0.50663112
A15: PV * Amount | B15: =B12*B13 -> -90000000 | C15: =C12*C13 -> 24107143 | D15: =D12*D13 -> 21524235 | E15: =E12*E13 -> 19218067 | F15: =F12*F13 -> 17158988 | G15: =G12*G13 -> 15320525 | H15: =H12*H13 -> 13679040 | I15: =SUM(C15:H15) -> 1.11008e+08
I17: =B15+I15 -> 21007998 | J17: NPV
J18: NPV is positive, so this project is beneficial for us

Sheet CASE 3
A1: Case 3
B2: Yr | C2: Yr | D2: Yr | E2: Yr | F2: Yr | G2: Yr | H2: Yr
A3: Particulars | B3: 0 | C3: 1 | D3: 2 | E3: 3 | F3: 4 | G3: 5 | H3: 6
A4: Sales Unit | C4: 120000 | D4: 120000 | E4: 120000 | F4: 120000 | G4: 120000 | H4: 120000 | K4: Yr
A5: Price PU | C5: 700 | D5: =C5+(C5)*5% -> 735 | E5: =D5+(D5)*5% -> 771.75 | F5: =E5+(E5)*5% -> 810.3375 | G5: =F5+(F5)*5% -> 850.85438 | H5: =G5+(G5)*5% -> 893.39709
A6: Revenue (A) | C6: =C4*C5 -> 84000000 | D6: =D4*D5 -> 88200000 | E6: =E4*E5 -> 92610000 | F6: =F4*F5 -> 97240500 | G6: =G4*G5 -> 102102525 | H6: =H4*H5 -> 1.0720765e+08
A7: Cost PU | C7: 535 | D7: =C7+(C7)*5% -> 561.75 | E7: =D7+(D7)*5% -> 589.8375 | F7: =E7+(E7)*5% -> 619.32938 | G7: =F7+(F7)*5% -> 650.29584 | H7: =G7+(G7)*5% -> 682.81064
A8: Total Cost (B) | C8: =C4*C7 -> 64200000 | D8: =D4*D7 -> 67410000 | E8: =E4*E7 -> 70780500 | F8: =F4*F7 -> 74319525 | G8: =G4*G7 -> 78035501 | H8: =H4*H7 -> 81937276
A10: Operating Profit (A-B) | C10: =C6-C8 -> 19800000 | D10: =D6-D8 -> 20790000 | E10: =E6-E8 -> 21829500 | F10: =F6-F8 -> 22920975 | G10: =G6-G8 -> 24067024 | H10: =H6-H8 -> 25270375
A12: Net (Outflow)/Inflow | B12: =-(15000000*4) -> -60000000 | C12: =C10 -> 19800000 | D12: =D10 -> 20790000 | E12: =E10 -> 21829500 | F12: =F10 -> 22920975 | G12: =G10 -> 24067024 | H12: =H10 -> 25270375
A13: PV @ 12 % | B13: 1 | C13: 0.89285714 | D13: 0.79719388 | E13: 0.71178025 | F13: 0.63551808 | G13: 0.56742686 | H13: 0.50663112
A15: PV * Amount | B15: =B12*B13 -> -60000000 | C15: =C12*C13 -> 17678571 | D15: =D12*D13 -> 16573661 | E15: =E12*E13 -> 15537807 | F15: =F12*F13 -> 14566694 | G15: =G12*G13 -> 13656276 | H15: =H12*H13 -> 12802758 | I15: =SUM(C15:H15) -> 90815767
I17: =B15+I15 -> 30815767 | J17: NPV
J18: NPV is positive, so this project is beneficial for us

Sheet CASE 4
A1: Case 4
B2: Yr | C2: Yr | D2: Yr | E2: Yr | F2: Yr | G2: Yr | H2: Yr
A3: Particulars | B3: 0 | C3: 1 | D3: 2 | E3: 3 | F3: 4 | G3: 5 | H3: 6
A4: Sales Unit | C4: 120000 | D4: 120000 | E4: 120000 | F4: 120000 | G4: 120000 | H4: 120000 | K4: Yr
A5: Price PU | C5: 700 | D5: =C5+(C5)*5% -> 735 | E5: =D5+(D5)*5% -> 771.75 | F5: =E5+(E5)*5% -> 810.3375 | G5: =F5+(F5)*5% -> 850.85438 | H5: =G5+(G5)*5% -> 893.39709
A6: Revenue (A) | C6: =C4*C5 -> 84000000 | D6: =D4*D5 -> 88200000 | E6: =E4*E5 -> 92610000 | F6: =F4*F5 -> 97240500 | G6: =G4*G5 -> 102102525 | H6: =H4*H5 -> 1.0720765e+08
A7: Cost PU | C7: 535 | D7: =C7+(C7)*5% -> 561.75 | E7: =D7+(D7)*5% -> 589.8375 | F7: =E7+(E7)*5% -> 619.32938 | G7: =F7+(F7)*5% -> 650.29584 | H7: =G7+(G7)*5% -> 682.81064
A8: Total Cost (B) | C8: =C4*C7 -> 64200000 | D8: =D4*D7 -> 67410000 | E8: =E4*E7 -> 70780500 | F8: =F4*F7 -> 74319525 | G8: =G4*G7 -> 78035501 | H8: =H4*H7 -> 81937276
A10: Operating Profit (A-B) | C10: =C6-C8 -> 19800000 | D10: =D6-D8 -> 20790000 | E10: =E6-E8 -> 21829500 | F10: =F6-F8 -> 22920975 | G10: =G6-G8 -> 24067024 | H10: =H6-H8 -> 25270375
A12: Net (Outflow)/Inflow | B12: -90000000 | C12: =C10 -> 19800000 | D12: =D10 -> 20790000 | E12: =E10 -> 21829500 | F12: =F10 -> 22920975 | G12: =G10 -> 24067024 | H12: =H10 -> 25270375
A13: PV @ 12 % | B13: 1 | C13: 0.89285714 | D13: 0.79719388 | E13: 0.71178025 | F13: 0.63551808 | G13: 0.56742686 | H13: 0.50663112
A15: PV * Amount | B15: =B12*B13 -> -90000000 | C15: =C12*C13 -> 17678571 | D15: =D12*D13 -> 16573661 | E15: =E12*E13 -> 15537807 | F15: =F12*F13 -> 14566694 | G15: =G12*G13 -> 13656276 | H15: =H12*H13 -> 12802758 | I15: =SUM(C15:H15) -> 90815767
I17: =B15+I15 -> 815767.05 | J17: NPV
J18: NPV is positive, so this project is beneficial for us

Sheet BASIC CALCULATIONS
B1: Option 1 | C1: Option 2 | D1: Option 3 | E1: PV Factor | F1: Option 1 | G1: Option 2 | H1: Option 3
A2: Year | B2: Amount | C2: Amount | D2: Amount | E2: PV @ 10% | F2: PV * Amt | G2: PV * Amt | H2: PV * Amt | J2: =1/1.1 -> 0.90909091
A3: 0 | B3: -500000 | C3: -500000 | D3: -500000 | E3: 1 | F3: =B3*$E3 -> -500000 | G3: =C3*$E3 -> -500000 | H3: =D3*$E3 -> -500000 | J3: =J2/1.1 -> 0.82644628
A4: 1 | B4: 90000 | C4: 120000 | D4: 150000 | E4: 0.90909091 | F4: =B4*$E4 -> 81818.182 | G4: =C4*$E4 -> 109090.91 | H4: =D4*$E4 -> 136363.64 | J4: =J3/1.1 -> 0.7513148
A5: 2 | B5: 90000 | C5: 120000 | D5: 150000 | E5: 0.82644628 | F5: =B5*$E5 -> 74380.165 | G5: =C5*$E5 -> 99173.554 | H5: =D5*$E5 -> 123966.94 | J5: =J4/1.1 -> 0.68301346
A6: 3 | B6: 90000 | C6: 120000 | D6: 150000 | E6: 0.7513148 | F6: =B6*$E6 -> 67618.332 | G6: =C6*$E6 -> 90157.776 | H6: =D6*$E6 -> 112697.22 | J6: =J5/1.1 -> 0.62092132
A7: 4 | B7: 90000 | C7: 120000 | D7: 150000 | E7: 0.68301346 | F7: =B7*$E7 -> 61471.211 | G7: =C7*$E7 -> 81961.615 | H7: =D7*$E7 -> 102452.02
A8: 5 | B8: 90000 | C8: 120000 | D8: 150000 | E8: 0.62092132 | F8: =B8*$E8 -> 55882.919 | G8: =C8*$E8 -> 74510.559 | H8: =D8*$E8 -> 93138.198
F9: =SUM(F3:F8) -> -158829.19 | G9: =SUM(G3:G8) -> -45105.588 | H9: =SUM(H3:H8) -> 68618.015
C11: 120000
C12: 1.1
A13: Year | B13: 0 | C13: 1 | D13: 2 | E13: 3 | F13: 4 | G13: 5
A14: Amount | B14: -500000 | C14: 120000 | D14: 120000 | E14: 120000 | F14: 120000 | G14: 120000
C15: 1.1 | D15: 1.1 | E15: 1.1 | F15: 1.1 | G15: 1.1
D16: =D14/D15 -> 109090.91 | E16: =E14/E15 -> 109090.91 | F16: 1.1 | G16: 1.1
D17: 1.1 | E17: 1.1 | F17: 1.1 | G17: 1.1
D18: =D16/D17 -> 99173.554 | E18: =E16/E17 -> 99173.554 | F18: 1.1 | G18: 1.1
E19: 1.1 | G19: 1.1
E20: =E18/E19 -> 90157.776
B23: Cash outflow | C23: cash inflow
B24: -500000 | C24: =C14/C15 -> 109090.91 | D24: =D14/D15/D17 -> 99173.554 | E24: =E14/E15/E17/E19 -> 90157.776 | F24: =F14/F15/F16/F17/F18 -> 81961.615 | G24: =G14/G15/G16/G17/G18/G19 -> 74510.559 | I24: =SUM(C24:G24) -> 454894.41 | J24: =B24+I24 -> -45105.588 | K24: NPV -
B25: Yr0 | C25: Yr 0 | D25: yr 0
C27: =120000/110% -> 109090.91
A29: Year | B29: 0 | C29: 1 | D29: 2 | E29: 3 | F29: 4 | G29: 5
A30: Amount | B30: -500000 | C30: 150000 | D30: 150000 | E30: 150000 | F30: 150000 | G30: 150000
C31: 1.1 | D31: 1.1 | E31: 1.1 | F31: 1.1 | G31: 1.1
D32: =D30/D31 -> 136363.64 | E32: =E30/E31 -> 136363.64 | F32: 1.1 | G32: 1.1
D33: 1.1 | E33: 1.1 | F33: 1.1 | G33: 1.1
D34: =D32/D33 -> 123966.94 | E34: =E32/E33 -> 123966.94 | F34: 1.1 | G34: 1.1
E35: 1.1 | G35: 1.1
E36: =E34/E35 -> 112697.22
B39: Cash outflow | C39: cash inflow
B40: -500000 | C40: =C30/C31 -> 136363.64 | D40: =D30/D31/D33 -> 123966.94 | E40: =E30/E31/E33/E35 -> 112697.22 | F40: =F30/F31/F32/F33/F34 -> 102452.02 | G40: =G30/G31/G32/G33/G34/G35 -> 93138.198 | I40: =SUM(C40:G40) -> 568618.02 | J40: =B40+I40 -> 68618.015 | K40: NPV +
B41: Yr0 | C41: Yr 0 | D41: yr 0
